cidr/__init__.py
cidr/network_calculator.py
cidr/network_calculator_test.py
feeds/__init__.py
feeds/bandwidth_calculator.py
feeds/bandwidth_calculator_test.py
tests/__init__.py
tests/bandwidth_calculator_test.py
tests/network_calculator.py
networkcalculator-1.0.5.dist-info/LICENSE.txt
networkcalculator-1.0.5.dist-info/METADATA
networkcalculator-1.0.5.dist-info/WHEEL
networkcalculator-1.0.5.dist-info/top_level.txt
networkcalculator-1.0.5.dist-info/RECORD
