Metadata-Version: 2.1
Name: networkcalculator
Version: 1.0.5
Summary: A network calculator package
Home-page: https://gitlab.com/raymodbernard/networkcalculator
Author: Ray Bernard
Author-email: ray.bernard@outlook.com
Project-URL: Bug Tracker, https://gitlab.com/raymodbernard/networkcalculator/issues
Project-URL: repository, https://gitlab.com/raymodbernard/networkcalculator
Classifier: Development Status :: 3 - Alpha
Classifier: Intended Audience :: Developers
Classifier: License :: OSI Approved :: MIT License
Classifier: Programming Language :: Python :: 3
Classifier: Programming Language :: Python :: 3.6
Classifier: Programming Language :: Python :: 3.7
Classifier: Programming Language :: Python :: 3.8
Classifier: Programming Language :: Python :: 3.9
Classifier: Programming Language :: Python :: 3.10
Classifier: Programming Language :: Python :: 3.11
Requires-Python: >=3.6
License-File: LICENSE.txt
